README.md
setup.py
dabri7_hello_world.egg-info/PKG-INFO
dabri7_hello_world.egg-info/SOURCES.txt
dabri7_hello_world.egg-info/dependency_links.txt
dabri7_hello_world.egg-info/top_level.txt
sample_package/__init__.py
sample_package/sample.py